shillelagh/__init__.py
shillelagh/console.py
shillelagh/db.py
shillelagh/exceptions.py
shillelagh/fields.py
shillelagh/filters.py
shillelagh/functions.py
shillelagh/lib.py
shillelagh/py.typed
shillelagh/types.py
shillelagh/typing.py
shillelagh/adapters/__init__.py
shillelagh/adapters/base.py
shillelagh/adapters/registry.py
shillelagh/adapters/api/__init__.py
shillelagh/adapters/api/datasette.py
shillelagh/adapters/api/dbt_metricflow.py
shillelagh/adapters/api/generic_json.py
shillelagh/adapters/api/generic_xml.py
shillelagh/adapters/api/github.py
shillelagh/adapters/api/html_table.py
shillelagh/adapters/api/preset.py
shillelagh/adapters/api/s3select.py
shillelagh/adapters/api/socrata.py
shillelagh/adapters/api/system.py
shillelagh/adapters/api/weatherapi.py
shillelagh/adapters/api/gsheets/__init__.py
shillelagh/adapters/api/gsheets/adapter.py
shillelagh/adapters/api/gsheets/fields.py
shillelagh/adapters/api/gsheets/lib.py
shillelagh/adapters/api/gsheets/types.py
shillelagh/adapters/api/gsheets/typing.py
shillelagh/adapters/api/gsheets/parsing/__init__.py
shillelagh/adapters/api/gsheets/parsing/base.py
shillelagh/adapters/api/gsheets/parsing/date.py
shillelagh/adapters/api/gsheets/parsing/number.py
shillelagh/adapters/file/__init__.py
shillelagh/adapters/file/csvfile.py
shillelagh/adapters/memory/__init__.py
shillelagh/adapters/memory/holidays.py
shillelagh/adapters/memory/pandas.py
shillelagh/adapters/memory/virtual.py
shillelagh/backends/__init__.py
shillelagh/backends/apsw/__init__.py
shillelagh/backends/apsw/db.py
shillelagh/backends/apsw/vt.py
shillelagh/backends/apsw/dialects/__init__.py
shillelagh/backends/apsw/dialects/base.py
shillelagh/backends/apsw/dialects/gsheets.py
shillelagh/backends/apsw/dialects/safe.py
shillelagh/backends/multicorn/__init__.py
shillelagh/backends/multicorn/db.py
shillelagh/backends/multicorn/fdw.py
shillelagh/backends/multicorn/dialects/__init__.py
shillelagh/backends/multicorn/dialects/base.py
shillelagh/backends/sqlglot/db.py
shillelagh-1.4.0.dist-info/licenses/AUTHORS.rst
shillelagh-1.4.0.dist-info/licenses/LICENSE.txt
shillelagh-1.4.0.dist-info/METADATA
shillelagh-1.4.0.dist-info/WHEEL
shillelagh-1.4.0.dist-info/entry_points.txt
shillelagh-1.4.0.dist-info/top_level.txt
shillelagh-1.4.0.dist-info/RECORD
