Metadata-Version: 2.4
Name: shillelagh
Version: 1.4.0
Summary: Making it easy to query APIs via SQL
Home-page: https://github.com/betodealmeida/shillelagh/
Author: Beto Dealmeida
Author-email: roberto@dealmeida.net
License: mit
Project-URL: Documentation, https://shillelagh.readthedocs.io/
Platform: any
Classifier: Development Status :: 5 - Production/Stable
Classifier: Intended Audience :: Science/Research
Classifier: License :: OSI Approved :: MIT License
Classifier: Programming Language :: Python :: 3.9
Classifier: Programming Language :: Python :: 3.10
Classifier: Programming Language :: Python :: 3.11
Classifier: Programming Language :: Python :: 3.12
Classifier: Programming Language :: Python :: 3.13
Classifier: Programming Language :: SQL
Requires-Python: >=3.9
License-File: LICENSE.txt
License-File: AUTHORS.rst
Requires-Dist: importlib-metadata; python_version < "3.10"
Requires-Dist: apsw>=3.43.2.0
Requires-Dist: python_dateutil>=2.8.1
Requires-Dist: requests>=2.31.0
Requires-Dist: requests-cache>=0.7.1
Requires-Dist: sqlalchemy>=1.3
Requires-Dist: greenlet>=2.0.2
Requires-Dist: typing_extensions>=3.7.4.3
Requires-Dist: packaging
Provides-Extra: testing
Requires-Dist: PyYAML>=5.4; extra == "testing"
Requires-Dist: appdirs>=1.4.4; extra == "testing"
Requires-Dist: beautifulsoup4>=4.11.1; extra == "testing"
Requires-Dist: boto3>=1.24.28; extra == "testing"
Requires-Dist: codespell>=2.1.0; extra == "testing"
Requires-Dist: defusedxml>=0.7.1; extra == "testing"
Requires-Dist: dill>=0.3.6; extra == "testing"
Requires-Dist: flake8-pyproject>=1.2.3; extra == "testing"
Requires-Dist: freezegun>=1.1.0; extra == "testing"
Requires-Dist: google-auth>=1.23.0; extra == "testing"
Requires-Dist: holidays>=0.23; extra == "testing"
Requires-Dist: html5lib>=1.1; extra == "testing"
Requires-Dist: pandas>=1.2.2; extra == "testing"
Requires-Dist: pip-tools>=6.4.0; extra == "testing"
Requires-Dist: pre-commit>=2.13.0; extra == "testing"
Requires-Dist: pip-compile-multi>=2.6.3; extra == "testing"
Requires-Dist: prison>=0.2.1; extra == "testing"
Requires-Dist: prompt_toolkit>=3; extra == "testing"
Requires-Dist: psutil>=5.8.0; extra == "testing"
Requires-Dist: psycopg2-binary>=2.9.9; extra == "testing"
Requires-Dist: pyarrow>=14.0.1; extra == "testing"
Requires-Dist: pyfakefs>=4.3.3; extra == "testing"
Requires-Dist: pygments>=2.8; extra == "testing"
Requires-Dist: pylint>=2.16.2; extra == "testing"
Requires-Dist: pytest-cov>=2.11.1; extra == "testing"
Requires-Dist: pytest-integration==0.2.2; extra == "testing"
Requires-Dist: pytest-mock>=3.5.1; extra == "testing"
Requires-Dist: pytest>=7.2.0; extra == "testing"
Requires-Dist: python-graphql-client>=0.4.3; extra == "testing"
Requires-Dist: python-jsonpath>=0.10.3; extra == "testing"
Requires-Dist: requests-mock>=1.8.0; extra == "testing"
Requires-Dist: ruff>=0.3.7; extra == "testing"
Requires-Dist: sqlglot>=23.0.2; extra == "testing"
Requires-Dist: tabulate>=0.8.9; extra == "testing"
Requires-Dist: yarl>=1.8.1; extra == "testing"
Provides-Extra: all
Requires-Dist: PyYAML>=5.4; extra == "all"
Requires-Dist: appdirs>=1.4.4; extra == "all"
Requires-Dist: beautifulsoup4>=4.11.1; extra == "all"
Requires-Dist: boto3>=1.24.28; extra == "all"
Requires-Dist: defusedxml>=0.7.1; extra == "all"
Requires-Dist: google-auth>=1.23.0; extra == "all"
Requires-Dist: holidays>=0.23; extra == "all"
Requires-Dist: html5lib>=1.1; extra == "all"
Requires-Dist: pandas>=1.2.2; extra == "all"
Requires-Dist: prison>=0.2.1; extra == "all"
Requires-Dist: prompt_toolkit>=3; extra == "all"
Requires-Dist: psutil>=5.8.0; extra == "all"
Requires-Dist: psycopg2-binary>=2.9.9; extra == "all"
Requires-Dist: pyarrow>=14.0.1; extra == "all"
Requires-Dist: pygments>=2.8; extra == "all"
Requires-Dist: python-graphql-client>=0.4.3; extra == "all"
Requires-Dist: python-jsonpath>=0.10.3; extra == "all"
Requires-Dist: sqlglot>=23.0.2; extra == "all"
Requires-Dist: tabulate>=0.8.9; extra == "all"
Requires-Dist: yarl>=1.8.1; extra == "all"
Provides-Extra: docs
Requires-Dist: sphinx>=4.0.1; extra == "docs"
Provides-Extra: console
Requires-Dist: PyYAML>=5.4; extra == "console"
Requires-Dist: appdirs>=1.4.4; extra == "console"
Requires-Dist: prompt_toolkit>=3; extra == "console"
Requires-Dist: pygments>=2.8; extra == "console"
Requires-Dist: tabulate>=0.8.9; extra == "console"
Provides-Extra: dbtmetricflowapi
Requires-Dist: pyarrow>=14.0.1; extra == "dbtmetricflowapi"
Requires-Dist: python-graphql-client>=0.4.3; extra == "dbtmetricflowapi"
Requires-Dist: sqlglot>=23.0.2; extra == "dbtmetricflowapi"
Provides-Extra: genericjsonapi
Requires-Dist: prison>=0.2.1; extra == "genericjsonapi"
Requires-Dist: python-jsonpath>=0.10.3; extra == "genericjsonapi"
Requires-Dist: yarl>=1.8.1; extra == "genericjsonapi"
Provides-Extra: genericxmlapi
Requires-Dist: defusedxml>=0.7.1; extra == "genericxmlapi"
Requires-Dist: prison>=0.2.1; extra == "genericxmlapi"
Requires-Dist: yarl>=1.8.1; extra == "genericxmlapi"
Provides-Extra: githubapi
Requires-Dist: python-jsonpath>=0.10.3; extra == "githubapi"
Provides-Extra: gsheetsapi
Requires-Dist: google-auth>=1.23.0; extra == "gsheetsapi"
Requires-Dist: pyopenssl>=24.0.0; extra == "gsheetsapi"
Provides-Extra: holidaysmemory
Requires-Dist: holidays>=0.23; extra == "holidaysmemory"
Provides-Extra: htmltableapi
Requires-Dist: beautifulsoup4>=4.11.1; extra == "htmltableapi"
Requires-Dist: html5lib>=1.1; extra == "htmltableapi"
Requires-Dist: pandas>=1.2.2; extra == "htmltableapi"
Provides-Extra: multicorn
Requires-Dist: psycopg2-binary>=2.9.9; extra == "multicorn"
Provides-Extra: pandasmemory
Requires-Dist: pandas>=1.2.2; extra == "pandasmemory"
Provides-Extra: s3selectapi
Requires-Dist: boto3>=1.24.28; extra == "s3selectapi"
Provides-Extra: systemapi
Requires-Dist: psutil>=5.8.0; extra == "systemapi"
Dynamic: license-file
